nlp_preprocessing_wrappers/__init__.py
nlp_preprocessing_wrappers/common/__init__.py
nlp_preprocessing_wrappers/common/logging.py
nlp_preprocessing_wrappers/common/utils.py
nlp_preprocessing_wrappers/data/__init__.py
nlp_preprocessing_wrappers/data/sentence.py
nlp_preprocessing_wrappers/data/word.py
nlp_preprocessing_wrappers/preprocessing/__init__.py
nlp_preprocessing_wrappers/preprocessing/sentence_splitters/__init__.py
nlp_preprocessing_wrappers/preprocessing/sentence_splitters/base_sentence_splitter.py
nlp_preprocessing_wrappers/preprocessing/sentence_splitters/spacy_sentence_splitter.py
nlp_preprocessing_wrappers/preprocessing/tokenizers/__init__.py
nlp_preprocessing_wrappers/preprocessing/tokenizers/base_tokenizer.py
nlp_preprocessing_wrappers/preprocessing/tokenizers/spacy_tokenizer.py
nlp_preprocessing_wrappers/preprocessing/tokenizers/stanza_tokenizer.py
nlp_preprocessing_wrappers/preprocessing/tokenizers/whitespace_tokenizer.py
nlp_preprocessing_wrappers-0.1.3.dist-info/METADATA
nlp_preprocessing_wrappers-0.1.3.dist-info/WHEEL
nlp_preprocessing_wrappers-0.1.3.dist-info/top_level.txt
nlp_preprocessing_wrappers-0.1.3.dist-info/RECORD
