Metadata-Version: 2.1
Name: nlp-preprocessing-wrappers
Version: 0.1.3
Summary: NLP Preprocessing Pipeline Wrappers
Home-page: https://github.com/Riccorl/preprocessing-wrappers
Author: Riccardo Orlando
Author-email: orlandoricc@gmail.com
License: Apache
Keywords: NLP deep learning transformer pytorch stanza spacy trankit preprocessing tokenization pos tagging lemmatization
Platform: UNKNOWN
Classifier: Programming Language :: Python :: 3
Classifier: License :: OSI Approved :: Apache Software License
Classifier: Operating System :: OS Independent
Requires-Python: >=3.6
Requires-Dist: spacy (<3.3,>=3.2)
Requires-Dist: stanza (<1.4,>=1.2)
Requires-Dist: overrides (<7.0.0,>=6.0.0)
Provides-Extra: all
Requires-Dist: torch (<1.11,>=1.5) ; extra == 'all'
Provides-Extra: torch
Requires-Dist: torch (<1.11,>=1.5) ; extra == 'torch'
